[{"line":1,"elements":[{"start_timestamp":"2024-11-03T05:20:24.520Z","before":[{"result":{"duration":1838227,"status":"passed"},"match":{"location":"memo1.ejercicio1.ClientSteps.beforeScenario()"}},{"result":{"duration":290272,"status":"passed"},"match":{"location":"memo1.ejercicio1.AccountOfficerSteps.beforeScenario()"}},{"result":{"duration":190265,"status":"passed"},"match":{"location":"memo1.ejercicio1.AccountSteps.beforeScenario()"}}],"line":2,"name":"Successfully create an account with default balance","description":"","id":"account-creation;successfully-create-an-account-with-default-balance","after":[{"result":{"duration":323463,"status":"passed"},"match":{"location":"memo1.ejercicio1.Hooks.afterScenario()"}}],"type":"scenario","keyword":"Scenario","steps":[{"result":{"duration":698512,"status":"passed"},"line":3,"name":"I create an account with CBU 123456789","match":{"arguments":[{"val":"123456789","offset":29}],"location":"memo1.ejercicio1.AccountSteps.createAccountWithDefaultBalance(long)"},"keyword":"Given "},{"result":{"duration":2844542,"status":"passed"},"line":4,"name":"The account balance should be 0.0","match":{"arguments":[{"val":"0.0","offset":30}],"location":"memo1.ejercicio1.AccountSteps.verifyAccountBalance(double)"},"keyword":"Then "}]},{"start_timestamp":"2024-11-03T05:20:24.578Z","before":[{"result":{"duration":871183,"status":"passed"},"match":{"location":"memo1.ejercicio1.ClientSteps.beforeScenario()"}},{"result":{"duration":308105,"status":"passed"},"match":{"location":"memo1.ejercicio1.AccountOfficerSteps.beforeScenario()"}},{"result":{"duration":291253,"status":"passed"},"match":{"location":"memo1.ejercicio1.AccountSteps.beforeScenario()"}}],"line":6,"name":"Successfully create an account with an initial balance","description":"","id":"account-creation;successfully-create-an-account-with-an-initial-balance","after":[{"result":{"duration":295912,"status":"passed"},"match":{"location":"memo1.ejercicio1.Hooks.afterScenario()"}}],"type":"scenario","keyword":"Scenario","steps":[{"result":{"duration":381081,"status":"passed"},"line":7,"name":"I create an account with CBU 987654321 and a balance of 500.0","match":{"arguments":[{"val":"987654321","offset":29},{"val":"500.0","offset":56}],"location":"memo1.ejercicio1.AccountSteps.createAccountWithInitialBalance(long,double)"},"keyword":"Given "},{"result":{"duration":322932,"status":"passed"},"line":8,"name":"The account balance should be 500.0","match":{"arguments":[{"val":"500.0","offset":30}],"location":"memo1.ejercicio1.AccountSteps.verifyAccountBalance(double)"},"keyword":"Then "}]}],"name":"Account creation","description":"","id":"account-creation","keyword":"Feature","uri":"file:src/test/resources/memo1/ejercicio1/account-creation.feature","tags":[]},{"line":1,"elements":[{"start_timestamp":"2024-11-03T05:20:24.617Z","before":[{"result":{"duration":299459,"status":"passed"},"match":{"location":"memo1.ejercicio1.ClientSteps.beforeScenario()"}},{"result":{"duration":307945,"status":"passed"},"match":{"location":"memo1.ejercicio1.AccountOfficerSteps.beforeScenario()"}},{"result":{"duration":281304,"status":"passed"},"match":{"location":"memo1.ejercicio1.AccountSteps.beforeScenario()"}}],"line":3,"name":"Successfully deposit money into an account","description":"","id":"depositing-money;successfully-deposit-money-into-an-account","after":[{"result":{"duration":255887,"status":"passed"},"match":{"location":"memo1.ejercicio1.Hooks.afterScenario()"}}],"type":"scenario","keyword":"Scenario","steps":[{"result":{"duration":906189,"status":"passed"},"line":4,"name":"An account with CBU 123456789 and a balance of 1000.0","match":{"arguments":[{"val":"123456789","offset":20},{"val":"1000.0","offset":47}],"location":"memo1.ejercicio1.AccountSteps.anAccountWithCBUAndBalance(long,double)"},"keyword":"Given "},{"result":{"duration":1328675,"status":"passed"},"line":5,"name":"I deposit 200.0 into the account","match":{"arguments":[{"val":"200.0","offset":10}],"location":"memo1.ejercicio1.AccountSteps.depositIntoAccount(double)"},"keyword":"When "},{"result":{"duration":313154,"status":"passed"},"line":6,"name":"The account balance should be 1200.0","match":{"arguments":[{"val":"1200.0","offset":30}],"location":"memo1.ejercicio1.AccountSteps.verifyAccountBalance(double)"},"keyword":"Then "}]},{"start_timestamp":"2024-11-03T05:20:24.676Z","before":[{"result":{"duration":169987,"status":"passed"},"match":{"location":"memo1.ejercicio1.ClientSteps.beforeScenario()"}},{"result":{"duration":324224,"status":"passed"},"match":{"location":"memo1.ejercicio1.AccountOfficerSteps.beforeScenario()"}},{"result":{"duration":267679,"status":"passed"},"match":{"location":"memo1.ejercicio1.AccountSteps.beforeScenario()"}}],"line":8,"name":"Cannot deposit a negative amount","description":"","id":"depositing-money;cannot-deposit-a-negative-amount","after":[{"result":{"duration":8573742,"status":"passed"},"match":{"location":"memo1.ejercicio1.Hooks.afterScenario()"}}],"type":"scenario","keyword":"Scenario","steps":[{"result":{"duration":182961,"status":"passed"},"line":9,"name":"An account with CBU 123456789 and a balance of 1000.0","match":{"arguments":[{"val":"123456789","offset":20},{"val":"1000.0","offset":47}],"location":"memo1.ejercicio1.AccountSteps.anAccountWithCBUAndBalance(long,double)"},"keyword":"Given "},{"result":{"duration":2274159,"status":"passed"},"line":10,"name":"I try to deposit -100.0 into the account","match":{"arguments":[{"val":"-100.0","offset":17}],"location":"memo1.ejercicio1.AccountSteps.depositIntoAccount(double)"},"keyword":"When "},{"result":{"duration":1445163,"status":"passed"},"line":11,"name":"The operation should be denied for negative amount","match":{"location":"memo1.ejercicio1.AccountSteps.verifyNegativeAmount()"},"keyword":"Then "},{"result":{"duration":301683,"status":"passed"},"line":12,"name":"The account balance should remain 1000.0","match":{"arguments":[{"val":"1000.0","offset":34}],"location":"memo1.ejercicio1.AccountSteps.verifyBalanceRemains(double)"},"keyword":"And "}]}],"name":"Depositing money","description":"","id":"depositing-money","keyword":"Feature","uri":"file:src/test/resources/memo1/ejercicio1/deposit.feature","tags":[]},{"line":1,"elements":[{"start_timestamp":"2024-11-03T05:20:24.738Z","before":[{"result":{"duration":121797,"status":"passed"},"match":{"location":"memo1.ejercicio1.ClientSteps.beforeScenario()"}},{"result":{"duration":339913,"status":"passed"},"match":{"location":"memo1.ejercicio1.AccountOfficerSteps.beforeScenario()"}},{"result":{"duration":327240,"status":"passed"},"match":{"location":"memo1.ejercicio1.AccountSteps.beforeScenario()"}}],"line":3,"name":"An account is successfully registered","description":"","id":"register-an-account-in-the-banking-system;an-account-is-successfully-registered","after":[{"result":{"duration":119984,"status":"passed"},"match":{"location":"memo1.ejercicio1.Hooks.afterScenario()"}}],"type":"scenario","keyword":"Scenario","steps":[{"result":{"duration":1309291,"status":"passed"},"line":4,"name":"an account officer with his branch, an client holder DNI \"42657569\" and two co-owners DNIs \"78945612\" , \"1234567\"","match":{"arguments":[{"val":"\"42657569\"","offset":57},{"val":"\"78945612\"","offset":91},{"val":"\"1234567\"","offset":104}],"location":"memo1.ejercicio1.AccountOfficerSteps.ownerAndCoowners(java.lang.String,java.lang.String,java.lang.String)"},"keyword":"Given "},{"result":{"duration":189483,"status":"passed"},"line":5,"name":"the account officer registers an account for them","match":{"location":"memo1.ejercicio1.AccountOfficerSteps.officerCreateAndRegisterAnAccount()"},"keyword":"When "},{"result":{"duration":145481,"status":"passed"},"line":6,"name":"The account officer automatically registers the account with his branch","match":{"location":"memo1.ejercicio1.AccountOfficerSteps.verifyCorrectBranch()"},"keyword":"Then "},{"result":{"duration":3309289,"status":"passed"},"line":7,"name":"enables its use for the account holder and co-owners","match":{"location":"memo1.ejercicio1.AccountOfficerSteps.verifyAccountCanDeposit()"},"keyword":"And "}]},{"start_timestamp":"2024-11-03T05:20:24.794Z","before":[{"result":{"duration":275353,"status":"passed"},"match":{"location":"memo1.ejercicio1.ClientSteps.beforeScenario()"}},{"result":{"duration":111578,"status":"passed"},"match":{"location":"memo1.ejercicio1.AccountOfficerSteps.beforeScenario()"}},{"result":{"duration":113111,"status":"passed"},"match":{"location":"memo1.ejercicio1.AccountSteps.beforeScenario()"}}],"line":9,"name":"An account is not registered for a customer who already has an account","description":"","id":"register-an-account-in-the-banking-system;an-account-is-not-registered-for-a-customer-who-already-has-an-account","after":[{"result":{"duration":139490,"status":"passed"},"match":{"location":"memo1.ejercicio1.Hooks.afterScenario()"}}],"type":"scenario","keyword":"Scenario","steps":[{"result":{"duration":185756,"status":"passed"},"line":10,"name":"an account officer with his branch office and an client DNI \"42657569\" who already has an account","match":{"arguments":[{"val":"\"42657569\"","offset":60}],"location":"memo1.ejercicio1.AccountOfficerSteps.anOwnerWithAnAccount(java.lang.String)"},"keyword":"Given "},{"result":{"duration":127338,"status":"passed"},"line":11,"name":"the account officer registers an new account for the client","match":{"location":"memo1.ejercicio1.AccountOfficerSteps.officerCreateAndRegisterAnAccount()"},"keyword":"When "},{"result":{"duration":386461,"status":"passed"},"line":12,"name":"the operation should be denied for trying to create an account to an client who already has an account","match":{"location":"memo1.ejercicio1.AccountOfficerSteps.verifyItAlreadyHasAnAccount()"},"keyword":"Then "}]},{"start_timestamp":"2024-11-03T05:20:24.824Z","before":[{"result":{"duration":331538,"status":"passed"},"match":{"location":"memo1.ejercicio1.ClientSteps.beforeScenario()"}},{"result":{"duration":189333,"status":"passed"},"match":{"location":"memo1.ejercicio1.AccountOfficerSteps.beforeScenario()"}},{"result":{"duration":191998,"status":"passed"},"match":{"location":"memo1.ejercicio1.AccountSteps.beforeScenario()"}}],"line":14,"name":"A cancelled account is registered successfully","description":"","id":"register-an-account-in-the-banking-system;a-cancelled-account-is-registered-successfully","after":[{"result":{"duration":200624,"status":"passed"},"match":{"location":"memo1.ejercicio1.Hooks.afterScenario()"}}],"type":"scenario","keyword":"Scenario","steps":[{"result":{"duration":360011,"status":"passed"},"line":15,"name":"an account officer with his branch and an client DNI \"42657569\" who has a cancelled account","match":{"arguments":[{"val":"\"42657569\"","offset":53}],"location":"memo1.ejercicio1.AccountOfficerSteps.anOwnerWithACancelledAccount(java.lang.String)"},"keyword":"Given "},{"result":{"duration":2911427,"status":"passed"},"line":16,"name":"the account officer registers the cancelled account","match":{"location":"memo1.ejercicio1.AccountOfficerSteps.officerRegisterAnAccount()"},"keyword":"When "},{"result":{"duration":307964,"status":"passed"},"line":17,"name":"The account officer automatically registers the account with his branch","match":{"location":"memo1.ejercicio1.AccountOfficerSteps.verifyCorrectBranch()"},"keyword":"Then "},{"result":{"duration":189903,"status":"passed"},"line":18,"name":"enables its use for the account holder and co-owners","match":{"location":"memo1.ejercicio1.AccountOfficerSteps.verifyAccountCanDeposit()"},"keyword":"And "}]}],"name":"Register an account in the Banking System","description":"","id":"register-an-account-in-the-banking-system","keyword":"Feature","uri":"file:src/test/resources/memo1/ejercicio1/registerAccount.feature","tags":[]},{"line":1,"elements":[{"start_timestamp":"2024-11-03T05:20:24.866Z","before":[{"result":{"duration":469004,"status":"passed"},"match":{"location":"memo1.ejercicio1.ClientSteps.beforeScenario()"}},{"result":{"duration":217205,"status":"passed"},"match":{"location":"memo1.ejercicio1.AccountOfficerSteps.beforeScenario()"}},{"result":{"duration":202487,"status":"passed"},"match":{"location":"memo1.ejercicio1.AccountSteps.beforeScenario()"}}],"line":3,"name":"A customer is successfully registered","description":"","id":"register-a-client-in-the-banking-system;a-customer-is-successfully-registered","after":[{"result":{"duration":510422,"status":"passed"},"match":{"location":"memo1.ejercicio1.Hooks.afterScenario()"}}],"type":"scenario","keyword":"Scenario","steps":[{"result":{"duration":322852,"status":"passed"},"line":4,"name":"client register his data (last name, first name, date of birth and address) with DNI \"42657569\" in the bank","match":{"arguments":[{"val":"\"42657569\"","offset":85}],"location":"memo1.ejercicio1.ClientSteps.createClientWithDNI(java.lang.String)"},"keyword":"Given "},{"result":{"duration":1290966,"status":"passed"},"line":5,"name":"the client with DNI \"42657569\" is in the System","match":{"arguments":[{"val":"\"42657569\"","offset":20}],"location":"memo1.ejercicio1.ClientSteps.verifyClientIsInTheSystem(java.lang.String)"},"keyword":"Then "}]},{"start_timestamp":"2024-11-03T05:20:24.909Z","before":[{"result":{"duration":487809,"status":"passed"},"match":{"location":"memo1.ejercicio1.ClientSteps.beforeScenario()"}},{"result":{"duration":242763,"status":"passed"},"match":{"location":"memo1.ejercicio1.AccountOfficerSteps.beforeScenario()"}},{"result":{"duration":213629,"status":"passed"},"match":{"location":"memo1.ejercicio1.AccountSteps.beforeScenario()"}}],"line":7,"name":"Unable to register the customer for invalid DNI","description":"","id":"register-a-client-in-the-banking-system;unable-to-register-the-customer-for-invalid-dni","after":[{"result":{"duration":2478621,"status":"passed"},"match":{"location":"memo1.ejercicio1.Hooks.afterScenario()"}}],"type":"scenario","keyword":"Scenario","steps":[{"result":{"duration":639122,"status":"passed"},"line":8,"name":"client try to register his data and puts an invalid DNI \"123456\"","match":{"arguments":[{"val":"\"123456\"","offset":56}],"location":"memo1.ejercicio1.ClientSteps.createClientWithDNI(java.lang.String)"},"keyword":"Given "},{"result":{"duration":208088,"status":"passed"},"line":9,"name":"the operation should be denied for invalid DNI","match":{"location":"memo1.ejercicio1.ClientSteps.verifyInvalidDNI()"},"keyword":"Then "},{"result":{"duration":1328076,"status":"passed"},"line":10,"name":"the client with DNI \"123456\" is not in the System","match":{"arguments":[{"val":"\"123456\"","offset":20}],"location":"memo1.ejercicio1.ClientSteps.verifyClientIsntInTheSystem(java.lang.String)"},"keyword":"And "}]},{"start_timestamp":"2024-11-03T05:20:24.946Z","before":[{"result":{"duration":216925,"status":"passed"},"match":{"location":"memo1.ejercicio1.ClientSteps.beforeScenario()"}},{"result":{"duration":224769,"status":"passed"},"match":{"location":"memo1.ejercicio1.AccountOfficerSteps.beforeScenario()"}},{"result":{"duration":198580,"status":"passed"},"match":{"location":"memo1.ejercicio1.AccountSteps.beforeScenario()"}}],"line":12,"name":"Unable to register the customer by DNI already registered in the bank","description":"","id":"register-a-client-in-the-banking-system;unable-to-register-the-customer-by-dni-already-registered-in-the-bank","after":[{"result":{"duration":201516,"status":"passed"},"match":{"location":"memo1.ejercicio1.Hooks.afterScenario()"}}],"type":"scenario","keyword":"Scenario","steps":[{"result":{"duration":296353,"status":"passed"},"line":13,"name":"client try to register his data and put in a DNI \"42657569\" already registered in the banking system","match":{"arguments":[{"val":"\"42657569\"","offset":49}],"location":"memo1.ejercicio1.ClientSteps.createClientWithDNIAlreadyExistentInTheSystem(java.lang.String)"},"keyword":"Given "},{"result":{"duration":201225,"status":"passed"},"line":14,"name":"the operation shoul be denied due to there is already a client registered with that DNI","match":{"location":"memo1.ejercicio1.ClientSteps.verifyClientAlreadyExists()"},"keyword":"Then "},{"result":{"duration":304808,"status":"passed"},"line":15,"name":"the client is not replaced in the system","match":{"location":"memo1.ejercicio1.ClientSteps.verifyReplacedClient()"},"keyword":"And "}]}],"name":"Register a client in the Banking System","description":"","id":"register-a-client-in-the-banking-system","keyword":"Feature","uri":"file:src/test/resources/memo1/ejercicio1/registerClient.feature","tags":[]},{"line":1,"elements":[{"start_timestamp":"2024-11-03T05:20:24.978Z","before":[{"result":{"duration":225009,"status":"passed"},"match":{"location":"memo1.ejercicio1.ClientSteps.beforeScenario()"}},{"result":{"duration":214329,"status":"passed"},"match":{"location":"memo1.ejercicio1.AccountOfficerSteps.beforeScenario()"}},{"result":{"duration":311872,"status":"passed"},"match":{"location":"memo1.ejercicio1.AccountSteps.beforeScenario()"}}],"line":3,"name":"Successfully transfer money from a account to other account using CBU","description":"","id":"transferring-money;successfully-transfer-money-from-a-account-to-other-account-using-cbu","after":[{"result":{"duration":3935696,"status":"passed"},"match":{"location":"memo1.ejercicio1.Hooks.afterScenario()"}}],"type":"scenario","keyword":"Scenario","steps":[{"result":{"duration":369289,"status":"passed"},"line":4,"name":"An account A with CBU 123456789 and a balance of 1000.0 and other account B with CBU 987654321 and a balance of 300.0","match":{"arguments":[{"val":"123456789","offset":22},{"val":"1000.0","offset":49},{"val":"987654321","offset":85},{"val":"300.0","offset":112}],"location":"memo1.ejercicio1.AccountSteps.twoAccountsWithCBUAndBalance(long,double,long,double)"},"keyword":"Given "},{"result":{"duration":278229,"status":"passed"},"line":5,"name":"account A transfer 200.0 to account B using CBU","match":{"arguments":[{"val":"200.0","offset":19}],"location":"memo1.ejercicio1.AccountSteps.transferFromAAccountToOtherAccount(double)"},"keyword":"When "},{"result":{"duration":249415,"status":"passed"},"line":6,"name":"The account A balance should be 800.0","match":{"arguments":[{"val":"800.0","offset":32}],"location":"memo1.ejercicio1.AccountSteps.verifyBalanceRemainsOfAccountA(double)"},"keyword":"Then "},{"result":{"duration":235930,"status":"passed"},"line":7,"name":"The account B balance should be 500.0","match":{"arguments":[{"val":"500.0","offset":32}],"location":"memo1.ejercicio1.AccountSteps.verifyBalanceRemainsOfAccountB(double)"},"keyword":"And "}]},{"start_timestamp":"2024-11-03T05:20:25.021Z","before":[{"result":{"duration":1032455,"status":"passed"},"match":{"location":"memo1.ejercicio1.ClientSteps.beforeScenario()"}},{"result":{"duration":834896,"status":"passed"},"match":{"location":"memo1.ejercicio1.AccountOfficerSteps.beforeScenario()"}},{"result":{"duration":214280,"status":"passed"},"match":{"location":"memo1.ejercicio1.AccountSteps.beforeScenario()"}}],"line":9,"name":"Cannot transfer more money than available balance","description":"","id":"transferring-money;cannot-transfer-more-money-than-available-balance","after":[{"result":{"duration":449007,"status":"passed"},"match":{"location":"memo1.ejercicio1.Hooks.afterScenario()"}}],"type":"scenario","keyword":"Scenario","steps":[{"result":{"duration":666142,"status":"passed"},"line":10,"name":"An account A with CBU 123456789 and a balance of 250.0 and other account B with CBU 987654321 and a balance of 400.0","match":{"arguments":[{"val":"123456789","offset":22},{"val":"250.0","offset":49},{"val":"987654321","offset":84},{"val":"400.0","offset":111}],"location":"memo1.ejercicio1.AccountSteps.twoAccountsWithCBUAndBalance(long,double,long,double)"},"keyword":"Given "},{"result":{"duration":325928,"status":"passed"},"line":11,"name":"account A try to transfer 300.0 to account B using CBU","match":{"arguments":[{"val":"300.0","offset":26}],"location":"memo1.ejercicio1.AccountSteps.transferFromAAccountToOtherAccount(double)"},"keyword":"When "},{"result":{"duration":566466,"status":"passed"},"line":12,"name":"The operation should be denied due to lack of funds in the account A","match":{"location":"memo1.ejercicio1.AccountSteps.verifyInsufficientFunds()"},"keyword":"Then "}]},{"start_timestamp":"2024-11-03T05:20:25.066Z","before":[{"result":{"duration":237804,"status":"passed"},"match":{"location":"memo1.ejercicio1.ClientSteps.beforeScenario()"}},{"result":{"duration":224849,"status":"passed"},"match":{"location":"memo1.ejercicio1.AccountOfficerSteps.beforeScenario()"}},{"result":{"duration":218918,"status":"passed"},"match":{"location":"memo1.ejercicio1.AccountSteps.beforeScenario()"}}],"line":14,"name":"Cannot transfer a negative amount","description":"","id":"transferring-money;cannot-transfer-a-negative-amount","after":[{"result":{"duration":434279,"status":"passed"},"match":{"location":"memo1.ejercicio1.Hooks.afterScenario()"}}],"type":"scenario","keyword":"Scenario","steps":[{"result":{"duration":521392,"status":"passed"},"line":15,"name":"An account A with CBU 123456789 and a balance of 1900.0 and other account B with CBU 987654321 and a balance of 1100.0","match":{"arguments":[{"val":"123456789","offset":22},{"val":"1900.0","offset":49},{"val":"987654321","offset":85},{"val":"1100.0","offset":112}],"location":"memo1.ejercicio1.AccountSteps.twoAccountsWithCBUAndBalance(long,double,long,double)"},"keyword":"Given "},{"result":{"duration":508508,"status":"passed"},"line":16,"name":"account A try to transfer -500 to account B using CBU","match":{"arguments":[{"val":"-500","offset":26}],"location":"memo1.ejercicio1.AccountSteps.transferFromAAccountToOtherAccount(double)"},"keyword":"When "},{"result":{"duration":672614,"status":"passed"},"line":17,"name":"The operation should be denied for negative amount","match":{"location":"memo1.ejercicio1.AccountSteps.verifyNegativeAmount()"},"keyword":"Then "},{"result":{"duration":3314349,"status":"passed"},"line":18,"name":"The account A balance should be 1900.0","match":{"arguments":[{"val":"1900.0","offset":32}],"location":"memo1.ejercicio1.AccountSteps.verifyBalanceRemainsOfAccountA(double)"},"keyword":"And "},{"result":{"duration":1706151,"status":"passed"},"line":19,"name":"The account B balance should be 1100.0","match":{"arguments":[{"val":"1100.0","offset":32}],"location":"memo1.ejercicio1.AccountSteps.verifyBalanceRemainsOfAccountB(double)"},"keyword":"And "}]},{"start_timestamp":"2024-11-03T05:20:25.114Z","before":[{"result":{"duration":296743,"status":"passed"},"match":{"location":"memo1.ejercicio1.ClientSteps.beforeScenario()"}},{"result":{"duration":288157,"status":"passed"},"match":{"location":"memo1.ejercicio1.AccountOfficerSteps.beforeScenario()"}},{"result":{"duration":387983,"status":"passed"},"match":{"location":"memo1.ejercicio1.AccountSteps.beforeScenario()"}}],"line":21,"name":"Failed transfer due to nonexistent CBU","description":"","id":"transferring-money;failed-transfer-due-to-nonexistent-cbu","after":[{"result":{"duration":204552,"status":"passed"},"match":{"location":"memo1.ejercicio1.Hooks.afterScenario()"}}],"type":"scenario","keyword":"Scenario","steps":[{"result":{"duration":400536,"status":"passed"},"line":22,"name":"An account A with CBU 123456789 and a balance of 400.0, an account B with CBU 987654321 and a balance of 1000.0 and a nonexistent CBU","match":{"arguments":[{"val":"123456789","offset":22},{"val":"400.0","offset":49},{"val":"987654321","offset":78},{"val":"1000.0","offset":105}],"location":"memo1.ejercicio1.AccountSteps.twoAccountsWithCBUAndBalance(long,double,long,double)"},"keyword":"Given "},{"result":{"duration":765828,"status":"passed"},"line":23,"name":"account A try to transfer 300.0 to account B but enter a nonexistent CBU","match":{"arguments":[{"val":"300.0","offset":26}],"location":"memo1.ejercicio1.AccountSteps.accountTryToTransferToAAccountButEnterAnNonexistentCBU(double)"},"keyword":"When "},{"result":{"duration":330186,"status":"passed"},"line":24,"name":"The operation should be denied for entering a non-existent CBU","match":{"location":"memo1.ejercicio1.AccountSteps.verifyNonexistentCBU()"},"keyword":"Then "},{"result":{"duration":5829677,"status":"passed"},"line":25,"name":"The account A balance should be 400.0","match":{"arguments":[{"val":"400.0","offset":32}],"location":"memo1.ejercicio1.AccountSteps.verifyBalanceRemainsOfAccountA(double)"},"keyword":"And "},{"result":{"duration":1151695,"status":"passed"},"line":26,"name":"The account B balance should be 1000.0","match":{"arguments":[{"val":"1000.0","offset":32}],"location":"memo1.ejercicio1.AccountSteps.verifyBalanceRemainsOfAccountB(double)"},"keyword":"And "}]},{"start_timestamp":"2024-11-03T05:20:25.157Z","before":[{"result":{"duration":216012,"status":"passed"},"match":{"location":"memo1.ejercicio1.ClientSteps.beforeScenario()"}},{"result":{"duration":173945,"status":"passed"},"match":{"location":"memo1.ejercicio1.AccountOfficerSteps.beforeScenario()"}},{"result":{"duration":201887,"status":"passed"},"match":{"location":"memo1.ejercicio1.AccountSteps.beforeScenario()"}}],"line":28,"name":"Successfully transfer money from a account to other account using Alias","description":"","id":"transferring-money;successfully-transfer-money-from-a-account-to-other-account-using-alias","after":[{"result":{"duration":190925,"status":"passed"},"match":{"location":"memo1.ejercicio1.Hooks.afterScenario()"}}],"type":"scenario","keyword":"Scenario","steps":[{"result":{"duration":297154,"status":"passed"},"line":29,"name":"An account A with alias \"uno.dos.tres\" and a balance of 600.0 and other account B with alias \"tres.dos.uno\" and a balance of 800.0","match":{"arguments":[{"val":"\"uno.dos.tres\"","offset":24},{"val":"600.0","offset":56},{"val":"\"tres.dos.uno\"","offset":93},{"val":"800.0","offset":125}],"location":"memo1.ejercicio1.AccountSteps.twoAccountsWithAliasAndBalance(java.lang.String,double,java.lang.String,double)"},"keyword":"Given "},{"result":{"duration":214730,"status":"passed"},"line":30,"name":"account A transfer 350.0 to account B using alias","match":{"arguments":[{"val":"350.0","offset":19}],"location":"memo1.ejercicio1.AccountSteps.transferFromAAccountToOtherAccount(double)"},"keyword":"When "},{"result":{"duration":226362,"status":"passed"},"line":31,"name":"The account A balance should be 250.0","match":{"arguments":[{"val":"250.0","offset":32}],"location":"memo1.ejercicio1.AccountSteps.verifyBalanceRemainsOfAccountA(double)"},"keyword":"Then "},{"result":{"duration":214640,"status":"passed"},"line":32,"name":"The account B balance should be 1150.0","match":{"arguments":[{"val":"1150.0","offset":32}],"location":"memo1.ejercicio1.AccountSteps.verifyBalanceRemainsOfAccountB(double)"},"keyword":"And "}]},{"start_timestamp":"2024-11-03T05:20:25.177Z","before":[{"result":{"duration":741893,"status":"passed"},"match":{"location":"memo1.ejercicio1.ClientSteps.beforeScenario()"}},{"result":{"duration":1427641,"status":"passed"},"match":{"location":"memo1.ejercicio1.AccountOfficerSteps.beforeScenario()"}},{"result":{"duration":1054295,"status":"passed"},"match":{"location":"memo1.ejercicio1.AccountSteps.beforeScenario()"}}],"line":34,"name":"Failed transfer due to nonexistent Alias","description":"","id":"transferring-money;failed-transfer-due-to-nonexistent-alias","after":[{"result":{"duration":575402,"status":"passed"},"match":{"location":"memo1.ejercicio1.Hooks.afterScenario()"}}],"type":"scenario","keyword":"Scenario","steps":[{"result":{"duration":284069,"status":"passed"},"line":35,"name":"An account A with alias \"uno.dos.tres\" and a balance of 960.0, an account B with alias \"tres.dos.uno\" and a balance of 1230.0 and a nonexistent Alias","match":{"arguments":[{"val":"\"uno.dos.tres\"","offset":24},{"val":"960.0","offset":56},{"val":"\"tres.dos.uno\"","offset":87},{"val":"1230.0","offset":119}],"location":"memo1.ejercicio1.AccountSteps.twoAccountsWithAliasAndBalance(java.lang.String,double,java.lang.String,double)"},"keyword":"Given "},{"result":{"duration":276606,"status":"passed"},"line":36,"name":"account A try to transfer 300.0 to account B but enter a nonexistent Alias","match":{"arguments":[{"val":"300.0","offset":26}],"location":"memo1.ejercicio1.AccountSteps.accountTryToTransferToAAccountButEnterAnNonexistentCBU(double)"},"keyword":"When "},{"result":{"duration":202097,"status":"passed"},"line":37,"name":"The operation should be denied for entering a non-existent Alias","match":{"location":"memo1.ejercicio1.AccountSteps.theOperationShouldBeDeniedForEnteringANonExistentAlias()"},"keyword":"Then "},{"result":{"duration":362306,"status":"passed"},"line":38,"name":"The account A balance should be 960.0","match":{"arguments":[{"val":"960.0","offset":32}],"location":"memo1.ejercicio1.AccountSteps.verifyBalanceRemainsOfAccountA(double)"},"keyword":"And "},{"result":{"duration":239878,"status":"passed"},"line":39,"name":"The account B balance should be 1230.0","match":{"arguments":[{"val":"1230.0","offset":32}],"location":"memo1.ejercicio1.AccountSteps.verifyBalanceRemainsOfAccountB(double)"},"keyword":"And "}]},{"start_timestamp":"2024-11-03T05:20:25.201Z","before":[{"result":{"duration":235088,"status":"passed"},"match":{"location":"memo1.ejercicio1.ClientSteps.beforeScenario()"}},{"result":{"duration":190034,"status":"passed"},"match":{"location":"memo1.ejercicio1.AccountOfficerSteps.beforeScenario()"}},{"result":{"duration":197358,"status":"passed"},"match":{"location":"memo1.ejercicio1.AccountSteps.beforeScenario()"}}],"line":41,"name":"Sender account cannot transfer if it isn't registered","description":"","id":"transferring-money;sender-account-cannot-transfer-if-it-isn-t-registered","after":[{"result":{"duration":184564,"status":"passed"},"match":{"location":"memo1.ejercicio1.Hooks.afterScenario()"}}],"type":"scenario","keyword":"Scenario","steps":[{"result":{"duration":322251,"status":"passed"},"line":42,"name":"an unregistered account A with CBU 987654321 and a balance of 800.0 and other account B with CBU 123456789","match":{"arguments":[{"val":"987654321","offset":35},{"val":"800.0","offset":62},{"val":"123456789","offset":97}],"location":"memo1.ejercicio1.AccountSteps.unregisteredSenderAccountAndOtherAccount(long,double,long)"},"keyword":"Given "},{"result":{"duration":242913,"status":"passed"},"line":43,"name":"account A transfer 700.0 to account B","match":{"arguments":[{"val":"700.0","offset":19}],"location":"memo1.ejercicio1.AccountSteps.transferFromAAccountToOtherAccount(double)"},"keyword":"When "},{"result":{"duration":176790,"status":"passed"},"line":44,"name":"The operation should be denied for pending account to be registered","match":{"location":"memo1.ejercicio1.AccountSteps.verifyIsThereUnregisteredAccount()"},"keyword":"Then "},{"result":{"duration":234287,"status":"passed"},"line":45,"name":"The account A balance should be 800.0","match":{"arguments":[{"val":"800.0","offset":32}],"location":"memo1.ejercicio1.AccountSteps.verifyBalanceRemainsOfAccountA(double)"},"keyword":"And "},{"result":{"duration":657406,"status":"passed"},"line":46,"name":"The account B balance should be 0.0","match":{"arguments":[{"val":"0.0","offset":32}],"location":"memo1.ejercicio1.AccountSteps.verifyBalanceRemainsOfAccountB(double)"},"keyword":"And "}]},{"start_timestamp":"2024-11-03T05:20:25.225Z","before":[{"result":{"duration":113772,"status":"passed"},"match":{"location":"memo1.ejercicio1.ClientSteps.beforeScenario()"}},{"result":{"duration":89076,"status":"passed"},"match":{"location":"memo1.ejercicio1.AccountOfficerSteps.beforeScenario()"}},{"result":{"duration":62898,"status":"passed"},"match":{"location":"memo1.ejercicio1.AccountSteps.beforeScenario()"}}],"line":48,"name":"Receiver account cannot receive a transferring if it isn't registered","description":"","id":"transferring-money;receiver-account-cannot-receive-a-transferring-if-it-isn-t-registered","after":[{"result":{"duration":80911,"status":"passed"},"match":{"location":"memo1.ejercicio1.Hooks.afterScenario()"}}],"type":"scenario","keyword":"Scenario","steps":[{"result":{"duration":227865,"status":"passed"},"line":49,"name":"an account A with CBU 987654321 and a balance of 900.0 and an unregistered account B with CBU 123456789","match":{"arguments":[{"val":"987654321","offset":22},{"val":"900.0","offset":49},{"val":"123456789","offset":94}],"location":"memo1.ejercicio1.AccountSteps.unregisteredReceiverAccountAndOtherAccount(long,double,long)"},"keyword":"Given "},{"result":{"duration":605228,"status":"passed"},"line":50,"name":"account A transfer 150.0 to account B","match":{"arguments":[{"val":"150.0","offset":19}],"location":"memo1.ejercicio1.AccountSteps.transferFromAAccountToOtherAccount(double)"},"keyword":"When "},{"result":{"duration":81673,"status":"passed"},"line":51,"name":"The operation should be denied for pending account to be registered","match":{"location":"memo1.ejercicio1.AccountSteps.verifyIsThereUnregisteredAccount()"},"keyword":"Then "},{"result":{"duration":113471,"status":"passed"},"line":52,"name":"The account A balance should be 900.0","match":{"arguments":[{"val":"900.0","offset":32}],"location":"memo1.ejercicio1.AccountSteps.verifyBalanceRemainsOfAccountA(double)"},"keyword":"And "},{"result":{"duration":125614,"status":"passed"},"line":53,"name":"The account B balance should be 0.0","match":{"arguments":[{"val":"0.0","offset":32}],"location":"memo1.ejercicio1.AccountSteps.verifyBalanceRemainsOfAccountB(double)"},"keyword":"And "}]}],"name":"Transferring money","description":"","id":"transferring-money","keyword":"Feature","uri":"file:src/test/resources/memo1/ejercicio1/transfer.feature","tags":[]},{"line":1,"elements":[{"start_timestamp":"2024-11-03T05:20:25.241Z","before":[{"result":{"duration":326219,"status":"passed"},"match":{"location":"memo1.ejercicio1.ClientSteps.beforeScenario()"}},{"result":{"duration":75250,"status":"passed"},"match":{"location":"memo1.ejercicio1.AccountOfficerSteps.beforeScenario()"}},{"result":{"duration":85058,"status":"passed"},"match":{"location":"memo1.ejercicio1.AccountSteps.beforeScenario()"}}],"line":3,"name":"Successfully withdraw money when the balance is sufficient","description":"","id":"withdrawing-money;successfully-withdraw-money-when-the-balance-is-sufficient","after":[{"result":{"duration":79888,"status":"passed"},"match":{"location":"memo1.ejercicio1.Hooks.afterScenario()"}}],"type":"scenario","keyword":"Scenario","steps":[{"result":{"duration":112109,"status":"passed"},"line":4,"name":"An account with CBU 123456789 and a balance of 1000.0","match":{"arguments":[{"val":"123456789","offset":20},{"val":"1000.0","offset":47}],"location":"memo1.ejercicio1.AccountSteps.anAccountWithCBUAndBalance(long,double)"},"keyword":"Given "},{"result":{"duration":864962,"status":"passed"},"line":5,"name":"I withdraw 300.0 from the account","match":{"arguments":[{"val":"300.0","offset":11}],"location":"memo1.ejercicio1.AccountSteps.withdrawFromAccount(double)"},"keyword":"When "},{"result":{"duration":259404,"status":"passed"},"line":6,"name":"The account balance should be 700.0","match":{"arguments":[{"val":"700.0","offset":30}],"location":"memo1.ejercicio1.AccountSteps.verifyAccountBalance(double)"},"keyword":"Then "}]},{"start_timestamp":"2024-11-03T05:20:25.253Z","before":[{"result":{"duration":88114,"status":"passed"},"match":{"location":"memo1.ejercicio1.ClientSteps.beforeScenario()"}},{"result":{"duration":79899,"status":"passed"},"match":{"location":"memo1.ejercicio1.AccountOfficerSteps.beforeScenario()"}},{"result":{"duration":72596,"status":"passed"},"match":{"location":"memo1.ejercicio1.AccountSteps.beforeScenario()"}}],"line":8,"name":"Cannot withdraw more money than available balance","description":"","id":"withdrawing-money;cannot-withdraw-more-money-than-available-balance","after":[{"result":{"duration":227885,"status":"passed"},"match":{"location":"memo1.ejercicio1.Hooks.afterScenario()"}}],"type":"scenario","keyword":"Scenario","steps":[{"result":{"duration":144430,"status":"passed"},"line":9,"name":"An account with CBU 123456789 and a balance of 1000.0","match":{"arguments":[{"val":"123456789","offset":20},{"val":"1000.0","offset":47}],"location":"memo1.ejercicio1.AccountSteps.anAccountWithCBUAndBalance(long,double)"},"keyword":"Given "},{"result":{"duration":935764,"status":"passed"},"line":10,"name":"I try to withdraw 1100.0 from the account","match":{"arguments":[{"val":"1100.0","offset":18}],"location":"memo1.ejercicio1.AccountSteps.withdrawFromAccount(double)"},"keyword":"When "},{"result":{"duration":839955,"status":"passed"},"line":11,"name":"The operation should be denied due to insufficient funds","match":{"location":"memo1.ejercicio1.AccountSteps.verifyInsufficientFunds()"},"keyword":"Then "},{"result":{"duration":242853,"status":"passed"},"line":12,"name":"The account balance should remain 1000.0","match":{"arguments":[{"val":"1000.0","offset":34}],"location":"memo1.ejercicio1.AccountSteps.verifyBalanceRemains(double)"},"keyword":"And "}]}],"name":"Withdrawing money","description":"","id":"withdrawing-money","keyword":"Feature","uri":"file:src/test/resources/memo1/ejercicio1/withdraw.feature","tags":[]}]